{"g": {"mid": 1639210919201, "gid": "0022100389", "gdte": "2021-12-10", "htm": "2021-12-10T19:00:00", "vtm": "2021-12-10T17:00:00", "etm": "2021-12-10T20:00:00", "gdtutc": "2021-12-11", "utctm": "01:00", "ac": "Oklahoma City", "as": "OK", "gcode": "20211210/LALOKC", "next": "http://data.nba.com/data/v2015/json/mobile_teams/nba/2021/scores/gamedetail/0022100389_gamedetail.json", "ar": 0, "p": 4, "st": 3, "stt": "Final", "cl": "00:00.0", "lpla": {"evt": 654, "cl": "00:00.0", "de": "End Period", "locX": 0, "locY": -80, "opt1": 0, "opt2": 0, "mtype": 0, "etype": 13, "opid": "", "tid": 0, "pid": 0, "hs": 95, "vs": 116, "epid": "", "oftid": 1610612747}, "vls": {"q1": 32, "s": 116, "ftout": 2, "stout": 0, "ta": "LAL", "tstsg": {"fga": 87, "fgm": 41, "tpa": 42, "tpm": 19, "fta": 20, "ftm": 15, "oreb": 12, "dreb": 35, "reb": 47, "ast": 23, "stl": 12, "blk": 3, "pf": 14, "tov": 16, "fbpts": 6, "fbptsa": 6, "fbptsm": 3, "pip": 40, "pipa": 35, "pipm": 20, "ble": 29, "bpts": 41, "tf": 0, "scp": 19, "tmreb": 12, "tmtov": 0, "potov": 19}, "pstsg": [{"fn": "LeBron", "ln": "James", "num": "6", "pos": "SF", "min": 34, "sec": 41, "totsec": 2081, "fga": 20, "fgm": 13, "tpa": 6, "tpm": 4, "fta": 4, "ftm": 3, "oreb": 0, "dreb": 5, "reb": 5, "ast": 6, "stl": 3, "blk": 2, "pf": 2, "pts": 33, "tov": 2, "fbpts": 4, "fbptsa": 2, "fbptsm": 2, "pip": 16, "pipa": 11, "pipm": 8, "court": 0, "pid": 2544, "pm": 19, "blka": 0, "tf": 0, "status": "A", "memo": ""}, {"fn": "Talen", "ln": "Horton-Tucker", "num": "5", "pos": "PF", "min": 24, "sec": 42, "totsec": 1482, "fga": 7, "fgm": 4, "tpa": 3, "tpm": 2, "fta": 2, "ftm": 1, "oreb": 1, "dreb": 2, "reb": 3, "ast": 2, "stl": 1, "blk": 0, "pf": 2, "pts": 11, "tov": 2, "fbpts": 0, "fbptsa": 0, "fbptsm": 0, "pip": 4, "pipa": 3, "pipm": 2, "court": 0, "pid": 1629659, "pm": 12, "blka": 0, "tf": 0, "status": "A", "memo": ""}, {"fn": "Dwight", "ln": "Howard", "num": "39", "pos": "C", "min": 17, "sec": 28, "totsec": 1048, "fga": 1, "fgm": 0, "tpa": 0, "tpm": 0, "fta": 2, "ftm": 1, "oreb": 3, "dreb": 5, "reb": 8, "ast": 1, "stl": 0, "blk": 0, "pf": 1, "pts": 1, "tov": 2, "fbpts": 0, "fbptsa": 0, "fbptsm": 0, "pip": 0, "pipa": 1, "pipm": 0, "court": 0, "pid": 2730, "pm": 14, "blka": 0, "tf": 0, "status": "A", "memo": ""}, {"fn": "Avery", "ln": "Bradley", "num": "20", "pos": "SG", "min": 26, "sec": 26, "totsec": 1586, "fga": 14, "fgm": 8, "tpa": 8, "tpm": 6, "fta": 0, "ftm": 0, "oreb": 1, "dreb": 1, "reb": 2, "ast": 0, "stl": 4, "blk": 0, "pf": 2, "pts": 22, "tov": 0, "fbpts": 0, "fbptsa": 0, "fbptsm": 0, "pip": 4, "pipa": 5, "pipm": 2, "court": 0, "pid": 202340, "pm": 13, "blka": 1, "tf": 0, "status": "A", "memo": ""}, {"fn": "Russell", "ln": "Westbrook", "num": "0", "pos": "PG", "min": 33, "sec": 20, "totsec": 2000, "fga": 8, "fgm": 4, "tpa": 1, "tpm": 0, "fta": 0, "ftm": 0, "oreb": 2, "dreb": 7, "reb": 9, "ast": 7, "stl": 0, "blk": 1, "pf": 1, "pts": 8, "tov": 5, "fbpts": 2, "fbptsa": 1, "fbptsm": 1, "pip": 6, "pipa": 4, "pipm": 3, "court": 0, "pid": 201566, "pm": 18, "blka": 0, "tf": 0, "status": "A", "memo": ""}, {"fn": "Malik", "ln": "Monk", "num": "11", "pos": "", "min": 18, "sec": 16, "totsec": 1096, "fga": 9, "fgm": 2, "tpa": 6, "tpm": 1, "fta": 2, "ftm": 1, "oreb": 1, "dreb": 3, "reb": 4, "ast": 2, "stl": 1, "blk": 0, "pf": 2, "pts": 6, "tov": 1, "fbpts": 0, "fbptsa": 1, "fbptsm": 0, "pip": 2, "pipa": 2, "pipm": 1, "court": 1, "pid": 1628370, "pm": -2, "blka": 0, "tf": 0, "status": "A", "memo": ""}, {"fn": "Austin", "ln": "Reaves", "num": "15", "pos": "", "min": 27, "sec": 57, "totsec": 1677, "fga": 7, "fgm": 4, "tpa": 3, "tpm": 1, "fta": 4, "ftm": 4, "oreb": 1, "dreb": 4, "reb": 5, "ast": 2, "stl": 0, "blk": 0, "pf": 0, "pts": 13, "tov": 1, "fbpts": 0, "fbptsa": 0, "fbptsm": 0, "pip": 6, "pipa": 4, "pipm": 3, "court": 1, "pid": 1630559, "pm": 17, "blka": 0, "tf": 0, "status": "A", "memo": ""}, {"fn": "DeAndre", "ln": "Jordan", "num": "10", "pos": "", "min": 11, "sec": 2, "totsec": 662, "fga": 3, "fgm": 1, "tpa": 0, "tpm": 0, "fta": 2, "ftm": 1, "oreb": 0, "dreb": 4, "reb": 4, "ast": 0, "stl": 1, "blk": 0, "pf": 1, "pts": 3, "tov": 2, "fbpts": 0, "fbptsa": 0, "fbptsm": 0, "pip": 2, "pipa": 2, "pipm": 1, "court": 1, "pid": 201599, "pm": 1, "blka": 1, "tf": 0, "status": "A", "memo": ""}, {"fn": "Carmelo", "ln": "Anthony", "num": "7", "pos": "", "min": 24, "sec": 11, "totsec": 1451, "fga": 6, "fgm": 1, "tpa": 6, "tpm": 1, "fta": 4, "ftm": 4, "oreb": 1, "dreb": 3, "reb": 4, "ast": 3, "stl": 1, "blk": 0, "pf": 3, "pts": 7, "tov": 1, "fbpts": 0, "fbptsa": 1, "fbptsm": 0, "pip": 0, "pipa": 0, "pipm": 0, "court": 0, "pid": 2546, "pm": 12, "blka": 0, "tf": 0, "status": "A", "memo": ""}, {"fn": "Wayne", "ln": "Ellington", "num": "2", "pos": "", "min": 17, "sec": 41, "totsec": 1061, "fga": 9, "fgm": 3, "tpa": 8, "tpm": 3, "fta": 0, "ftm": 0, "oreb": 0, "dreb": 1, "reb": 1, "ast": 0, "stl": 1, "blk": 0, "pf": 0, "pts": 9, "tov": 0, "fbpts": 0, "fbptsa": 1, "fbptsm": 0, "pip": 0, "pipa": 1, "pipm": 0, "court": 1, "pid": 201961, "pm": -1, "blka": 1, "tf": 0, "status": "A", "memo": ""}, {"fn": "Kent", "ln": "Bazemore", "num": "9", "pos": "", "min": 4, "sec": 16, "totsec": 256, "fga": 3, "fgm": 1, "tpa": 1, "tpm": 1, "fta": 0, "ftm": 0, "oreb": 2, "dreb": 0, "reb": 2, "ast": 0, "stl": 0, "blk": 0, "pf": 0, "pts": 3, "tov": 0, "fbpts": 0, "fbptsa": 0, "fbptsm": 0, "pip": 0, "pipa": 2, "pipm": 0, "court": 1, "pid": 203145, "pm": 2, "blka": 0, "tf": 0, "status": "A", "memo": ""}, {"fn": "Anthony", "ln": "Davis", "num": "3", "pos": "", "min": 0, "sec": 0, "totsec": 0, "fga": 0, "fgm": 0, "tpa": 0, "tpm": 0, "fta": 0, "ftm": 0, "oreb": 0, "dreb": 0, "reb": 0, "ast": 0, "stl": 0, "blk": 0, "pf": 0, "pts": 0, "tov": 0, "fbpts": 0, "fbptsa": 0, "fbptsm": 0, "pip": 0, "pipa": 0, "pipm": 0, "court": 0, "pid": 203076, "pm": 0, "blka": 0, "tf": 0, "status": "A", "memo": ""}, {"fn": "Rajon", "ln": "Rondo", "num": "4", "pos": "", "min": 0, "sec": 0, "totsec": 0, "fga": 0, "fgm": 0, "tpa": 0, "tpm": 0, "fta": 0, "ftm": 0, "oreb": 0, "dreb": 0, "reb": 0, "ast": 0, "stl": 0, "blk": 0, "pf": 0, "pts": 0, "tov": 0, "fbpts": 0, "fbptsa": 0, "fbptsm": 0, "pip": 0, "pipa": 0, "pipm": 0, "court": 0, "pid": 200765, "pm": 0, "blka": 0, "tf": 0, "status": "A", "memo": ""}, {"fn": "Trevor", "ln": "Ariza", "num": "1", "pos": "", "min": 0, "sec": 0, "totsec": 0, "fga": 0, "fgm": 0, "tpa": 0, "tpm": 0, "fta": 0, "ftm": 0, "oreb": 0, "dreb": 0, "reb": 0, "ast": 0, "stl": 0, "blk": 0, "pf": 0, "pts": 0, "tov": 0, "fbpts": 0, "fbptsa": 0, "fbptsm": 0, "pip": 0, "pipa": 0, "pipm": 0, "court": 0, "pid": 2772, "pm": 0, "blka": 0, "tf": 0, "status": "I", "memo": ""}, {"fn": "Chaundee", "ln": "Brown Jr.", "num": "38", "pos": "", "min": 0, "sec": 0, "totsec": 0, "fga": 0, "fgm": 0, "tpa": 0, "tpm": 0, "fta": 0, "ftm": 0, "oreb": 0, "dreb": 0, "reb": 0, "ast": 0, "stl": 0, "blk": 0, "pf": 0, "pts": 0, "tov": 0, "fbpts": 0, "fbptsa": 0, "fbptsm": 0, "pip": 0, "pipa": 0, "pipm": 0, "court": 0, "pid": 1630602, "pm": 0, "blka": 0, "tf": 0, "status": "I", "memo": ""}, {"fn": "Jay", "ln": "Huff", "num": "34", "pos": "", "min": 0, "sec": 0, "totsec": 0, "fga": 0, "fgm": 0, "tpa": 0, "tpm": 0, "fta": 0, "ftm": 0, "oreb": 0, "dreb": 0, "reb": 0, "ast": 0, "stl": 0, "blk": 0, "pf": 0, "pts": 0, "tov": 0, "fbpts": 0, "fbptsa": 0, "fbptsm": 0, "pip": 0, "pipa": 0, "pipm": 0, "court": 0, "pid": 1630643, "pm": 0, "blka": 0, "tf": 0, "status": "I", "memo": ""}, {"fn": "Kendrick", "ln": "Nunn", "num": "12", "pos": "", "min": 0, "sec": 0, "totsec": 0, "fga": 0, "fgm": 0, "tpa": 0, "tpm": 0, "fta": 0, "ftm": 0, "oreb": 0, "dreb": 0, "reb": 0, "ast": 0, "stl": 0, "blk": 0, "pf": 0, "pts": 0, "tov": 0, "fbpts": 0, "fbptsa": 0, "fbptsm": 0, "pip": 0, "pipa": 0, "pipm": 0, "court": 0, "pid": 1629134, "pm": 0, "blka": 0, "tf": 0, "status": "I", "memo": ""}], "tn": "Lakers", "tc": "Los Angeles", "tid": 1610612747, "q2": 32, "q3": 29, "q4": 23, "ot1": 0, "ot2": 0, "ot3": 0, "ot4": 0, "ot5": 0, "ot6": 0, "ot7": 0, "ot8": 0, "ot9": 0, "ot10": 0}, "hls": {"q1": 18, "s": 95, "ftout": 1, "stout": 0, "ta": "OKC", "tstsg": {"fga": 96, "fgm": 38, "tpa": 44, "tpm": 10, "fta": 14, "ftm": 9, "oreb": 19, "dreb": 32, "reb": 51, "ast": 21, "stl": 9, "blk": 3, "pf": 17, "tov": 15, "fbpts": 8, "fbptsa": 7, "fbptsm": 4, "pip": 54, "pipa": 47, "pipm": 27, "ble": 2, "bpts": 44, "tf": 0, "scp": 14, "tmreb": 4, "tmtov": 0, "potov": 15}, "pstsg": [{"fn": "Luguentz", "ln": "Dort", "num": "5", "pos": "SF", "min": 32, "sec": 52, "totsec": 1972, "fga": 17, "fgm": 4, "tpa": 11, "tpm": 2, "fta": 2, "ftm": 1, "oreb": 0, "dreb": 0, "reb": 0, "ast": 2, "stl": 1, "blk": 0, "pf": 1, "pts": 11, "tov": 1, "fbpts": 2, "fbptsa": 2, "fbptsm": 1, "pip": 2, "pipa": 4, "pipm": 1, "court": 0, "pid": 1629652, "pm": -20, "blka": 1, "tf": 0, "status": "A", "memo": ""}, {"fn": "Darius", "ln": "Bazley", "num": "7", "pos": "PF", "min": 23, "sec": 48, "totsec": 1428, "fga": 7, "fgm": 3, "tpa": 5, "tpm": 1, "fta": 2, "ftm": 2, "oreb": 1, "dreb": 6, "reb": 7, "ast": 2, "stl": 3, "blk": 0, "pf": 1, "pts": 9, "tov": 1, "fbpts": 2, "fbptsa": 1, "fbptsm": 1, "pip": 4, "pipa": 2, "pipm": 2, "court": 0, "pid": 1629647, "pm": -14, "blka": 0, "tf": 0, "status": "A", "memo": ""}, {"fn": "Jeremiah", "ln": "Robinson-Earl", "num": "50", "pos": "C", "min": 26, "sec": 20, "totsec": 1580, "fga": 7, "fgm": 3, "tpa": 5, "tpm": 2, "fta": 0, "ftm": 0, "oreb": 4, "dreb": 5, "reb": 9, "ast": 1, "stl": 0, "blk": 0, "pf": 1, "pts": 8, "tov": 1, "fbpts": 0, "fbptsa": 1, "fbptsm": 0, "pip": 2, "pipa": 2, "pipm": 1, "court": 0, "pid": 1630526, "pm": -1, "blka": 1, "tf": 0, "status": "A", "memo": ""}, {"fn": "Josh", "ln": "Giddey", "num": "3", "pos": "SG", "min": 32, "sec": 3, "totsec": 1923, "fga": 12, "fgm": 5, "tpa": 5, "tpm": 0, "fta": 2, "ftm": 2, "oreb": 1, "dreb": 6, "reb": 7, "ast": 7, "stl": 1, "blk": 0, "pf": 2, "pts": 12, "tov": 3, "fbpts": 2, "fbptsa": 2, "fbptsm": 1, "pip": 10, "pipa": 6, "pipm": 5, "court": 0, "pid": 1630581, "pm": -14, "blka": 0, "tf": 0, "status": "A", "memo": ""}, {"fn": "Shai", "ln": "Gilgeous-Alexander", "num": "2", "pos": "PG", "min": 30, "sec": 21, "totsec": 1821, "fga": 12, "fgm": 5, "tpa": 3, "tpm": 1, "fta": 1, "ftm": 0, "oreb": 1, "dreb": 1, "reb": 2, "ast": 4, "stl": 0, "blk": 1, "pf": 1, "pts": 11, "tov": 2, "fbpts": 0, "fbptsa": 0, "fbptsm": 0, "pip": 8, "pipa": 8, "pipm": 4, "court": 0, "pid": 1628983, "pm": -16, "blka": 0, "tf": 0, "status": "A", "memo": ""}, {"fn": "Tre", "ln": "Mann", "num": "23", "pos": "", "min": 27, "sec": 45, "totsec": 1665, "fga": 15, "fgm": 8, "tpa": 8, "tpm": 3, "fta": 0, "ftm": 0, "oreb": 0, "dreb": 3, "reb": 3, "ast": 0, "stl": 1, "blk": 0, "pf": 3, "pts": 19, "tov": 0, "fbpts": 0, "fbptsa": 0, "fbptsm": 0, "pip": 10, "pipa": 7, "pipm": 5, "court": 1, "pid": 1630544, "pm": -7, "blka": 0, "tf": 0, "status": "A", "memo": ""}, {"fn": "Derrick", "ln": "Favors", "num": "15", "pos": "", "min": 12, "sec": 52, "totsec": 772, "fga": 6, "fgm": 4, "tpa": 1, "tpm": 0, "fta": 2, "ftm": 1, "oreb": 1, "dreb": 3, "reb": 4, "ast": 0, "stl": 0, "blk": 0, "pf": 2, "pts": 9, "tov": 0, "fbpts": 0, "fbptsa": 0, "fbptsm": 0, "pip": 8, "pipa": 5, "pipm": 4, "court": 0, "pid": 202324, "pm": -15, "blka": 0, "tf": 0, "status": "A", "memo": ""}, {"fn": "Aleksej", "ln": "Pokusevski", "num": "17", "pos": "", "min": 16, "sec": 50, "totsec": 1010, "fga": 8, "fgm": 3, "tpa": 4, "tpm": 1, "fta": 0, "ftm": 0, "oreb": 2, "dreb": 3, "reb": 5, "ast": 1, "stl": 1, "blk": 1, "pf": 3, "pts": 7, "tov": 1, "fbpts": 2, "fbptsa": 1, "fbptsm": 1, "pip": 4, "pipa": 4, "pipm": 2, "court": 1, "pid": 1630197, "pm": -11, "blka": 0, "tf": 0, "status": "A", "memo": ""}, {"fn": "Kenrich", "ln": "Williams", "num": "34", "pos": "", "min": 18, "sec": 45, "totsec": 1125, "fga": 5, "fgm": 0, "tpa": 2, "tpm": 0, "fta": 2, "ftm": 0, "oreb": 5, "dreb": 1, "reb": 6, "ast": 3, "stl": 1, "blk": 0, "pf": 1, "pts": 0, "tov": 2, "fbpts": 0, "fbptsa": 0, "fbptsm": 0, "pip": 0, "pipa": 3, "pipm": 0, "court": 0, "pid": 1629026, "pm": 0, "blka": 1, "tf": 0, "status": "A", "memo": ""}, {"fn": "Mike", "ln": "Muscala", "num": "33", "pos": "", "min": 4, "sec": 28, "totsec": 268, "fga": 3, "fgm": 1, "tpa": 0, "tpm": 0, "fta": 0, "ftm": 0, "oreb": 2, "dreb": 2, "reb": 4, "ast": 0, "stl": 0, "blk": 0, "pf": 1, "pts": 2, "tov": 2, "fbpts": 0, "fbptsa": 0, "fbptsm": 0, "pip": 2, "pipa": 2, "pipm": 1, "court": 0, "pid": 203488, "pm": -7, "blka": 0, "tf": 0, "status": "A", "memo": ""}, {"fn": "Paul", "ln": "Watson", "num": "8", "pos": "", "min": 4, "sec": 38, "totsec": 278, "fga": 0, "fgm": 0, "tpa": 0, "tpm": 0, "fta": 0, "ftm": 0, "oreb": 0, "dreb": 0, "reb": 0, "ast": 0, "stl": 1, "blk": 0, "pf": 1, "pts": 0, "tov": 0, "fbpts": 0, "fbptsa": 0, "fbptsm": 0, "pip": 0, "pipa": 0, "pipm": 0, "court": 1, "pid": 1628778, "pm": 0, "blka": 0, "tf": 0, "status": "A", "memo": ""}, {"fn": "Theo", "ln": "Maledon", "num": "11", "pos": "", "min": 4, "sec": 38, "totsec": 278, "fga": 1, "fgm": 1, "tpa": 0, "tpm": 0, "fta": 3, "ftm": 3, "oreb": 0, "dreb": 2, "reb": 2, "ast": 1, "stl": 0, "blk": 1, "pf": 0, "pts": 5, "tov": 1, "fbpts": 0, "fbptsa": 0, "fbptsm": 0, "pip": 2, "pipa": 1, "pipm": 1, "court": 1, "pid": 1630177, "pm": 0, "blka": 0, "tf": 0, "status": "A", "memo": ""}, {"fn": "Isaiah", "ln": "Roby", "num": "22", "pos": "", "min": 4, "sec": 38, "totsec": 278, "fga": 3, "fgm": 1, "tpa": 0, "tpm": 0, "fta": 0, "ftm": 0, "oreb": 2, "dreb": 0, "reb": 2, "ast": 0, "stl": 0, "blk": 0, "pf": 0, "pts": 2, "tov": 1, "fbpts": 0, "fbptsa": 0, "fbptsm": 0, "pip": 2, "pipa": 3, "pipm": 1, "court": 1, "pid": 1629676, "pm": 0, "blka": 0, "tf": 0, "status": "A", "memo": ""}, {"fn": "Gabriel", "ln": "Deck", "num": "6", "pos": "", "min": 0, "sec": 0, "totsec": 0, "fga": 0, "fgm": 0, "tpa": 0, "tpm": 0, "fta": 0, "ftm": 0, "oreb": 0, "dreb": 0, "reb": 0, "ast": 0, "stl": 0, "blk": 0, "pf": 0, "pts": 0, "tov": 0, "fbpts": 0, "fbptsa": 0, "fbptsm": 0, "pip": 0, "pipa": 0, "pipm": 0, "court": 0, "pid": 1630466, "pm": 0, "blka": 0, "tf": 0, "status": "A", "memo": ""}, {"fn": "Ty", "ln": "Jerome", "num": "16", "pos": "", "min": 0, "sec": 0, "totsec": 0, "fga": 0, "fgm": 0, "tpa": 0, "tpm": 0, "fta": 0, "ftm": 0, "oreb": 0, "dreb": 0, "reb": 0, "ast": 0, "stl": 0, "blk": 0, "pf": 0, "pts": 0, "tov": 0, "fbpts": 0, "fbptsa": 0, "fbptsm": 0, "pip": 0, "pipa": 0, "pipm": 0, "court": 0, "pid": 1629660, "pm": 0, "blka": 0, "tf": 0, "status": "A", "memo": ""}, {"fn": "Vit", "ln": "Krejci", "num": "27", "pos": "", "min": 0, "sec": 0, "totsec": 0, "fga": 0, "fgm": 0, "tpa": 0, "tpm": 0, "fta": 0, "ftm": 0, "oreb": 0, "dreb": 0, "reb": 0, "ast": 0, "stl": 0, "blk": 0, "pf": 0, "pts": 0, "tov": 0, "fbpts": 0, "fbptsa": 0, "fbptsm": 0, "pip": 0, "pipa": 0, "pipm": 0, "court": 0, "pid": 1630249, "pm": 0, "blka": 0, "tf": 0, "status": "I", "memo": ""}, {"fn": "Aaron", "ln": "Wiggins", "num": "21", "pos": "", "min": 0, "sec": 0, "totsec": 0, "fga": 0, "fgm": 0, "tpa": 0, "tpm": 0, "fta": 0, "ftm": 0, "oreb": 0, "dreb": 0, "reb": 0, "ast": 0, "stl": 0, "blk": 0, "pf": 0, "pts": 0, "tov": 0, "fbpts": 0, "fbptsa": 0, "fbptsm": 0, "pip": 0, "pipa": 0, "pipm": 0, "court": 0, "pid": 1630598, "pm": 0, "blka": 0, "tf": 0, "status": "I", "memo": ""}], "tn": "Thunder", "tc": "Oklahoma City", "tid": 1610612760, "q2": 27, "q3": 23, "q4": 27, "ot1": 0, "ot2": 0, "ot3": 0, "ot4": 0, "ot5": 0, "ot6": 0, "ot7": 0, "ot8": 0, "ot9": 0, "ot10": 0}, "offs": {"off": [{"fn": "Sean", "ln": "Corbin", "num": "33"}, {"fn": "John", "ln": "Goble", "num": "30"}, {"fn": "Ray", "ln": "Acosta", "num": "54"}]}, "an": "Paycom Center", "at": 16523, "gsts": {"lc": 3, "tt": 3}, "dur": "2:06"}}