{"resource": "shotchartdetail", "parameters": {"LeagueID": "00", "Season": "2021-22", "SeasonType": "Regular Season", "TeamID": 1610612762, "PlayerID": 0, "GameID": "0022100437", "Outcome": null, "Location": null, "Month": 0, "SeasonSegment": null, "DateFrom": null, "DateTo": null, "OpponentTeamID": 0, "VsConference": null, "VsDivision": null, "Position": null, "RookieYear": null, "GameSegment": null, "Period": 0, "LastNGames": 0, "ClutchTime": null, "AheadBehind": null, "PointDiff": null, "RangeType": null, "StartPeriod": null, "EndPeriod": null, "StartRange": null, "EndRange": null, "ContextFilter": "", "ContextMeasure": "FG_PCT"}, "resultSets": [{"name": "Shot_Chart_Detail", "headers": ["GRID_TYPE", "GAME_ID", "GAME_EVENT_ID", "PLAYER_ID", "PLAYER_NAME", "TEAM_ID", "TEAM_NAME", "PERIOD", "MINUTES_REMAINING", "SECONDS_REMAINING", "EVENT_TYPE", "ACTION_TYPE", "SHOT_TYPE", "SHOT_ZONE_BASIC", "SHOT_ZONE_AREA", "SHOT_ZONE_RANGE", "SHOT_DISTANCE", "LOC_X", "LOC_Y", "SHOT_ATTEMPTED_FLAG", "SHOT_MADE_FLAG", "GAME_DATE", "HTM", "VTM"], "rowSet": [["Shot Chart Detail", "0022100437", 9, 201144, "Mike Conley", 1610612762, "Utah Jazz", 1, 11, 24, "Missed Shot", "Jump Shot", "3PT Field Goal", "Above the Break 3", "Right Side Center(RC)", "24+ ft.", 26, 157, 211, 1, 0, "20211217", "UTA", "SAS"], ["Shot Chart Detail", "0022100437", 18, 203497, "Rudy Gobert", 1610612762, "Utah Jazz", 1, 10, 55, "Made Shot", "Alley Oop Dunk Shot", "2PT Field Goal", "Restricted Area", "Center(C)", "Less Than 8 ft.", 3, -25, 23, 1, 1, "20211217", "UTA", "SAS"], ["Shot Chart Detail", "0022100437", 23, 202711, "Bojan Bogdanovic", 1610612762, "Utah Jazz", 1, 10, 23, "Made Shot", "Fadeaway Jump Shot", "2PT Field Goal", "In The Paint (Non-RA)", "Center(C)", "8-16 ft.", 9, 33, 86, 1, 1, "20211217", "UTA", "SAS"], ["Shot Chart Detail", "0022100437", 28, 201144, "Mike Conley", 1610612762, "Utah Jazz", 1, 10, 9, "Made Shot", "Running Layup Shot", "2PT Field Goal", "Restricted Area", "Center(C)", "Less Than 8 ft.", 2, 20, 22, 1, 1, "20211217", "UTA", "SAS"], ["Shot Chart Detail", "0022100437", 33, 202711, "Bojan Bogdanovic", 1610612762, "Utah Jazz", 1, 9, 32, "Made Shot", "Cutting Layup Shot", "2PT Field Goal", "Restricted Area", "Center(C)", "Less Than 8 ft.", 3, 28, 25, 1, 1, "20211217", "UTA", "SAS"], ["Shot Chart Detail", "0022100437", 41, 1628378, "Donovan Mitchell", 1610612762, "Utah Jazz", 1, 8, 50, "Made Shot", "Driving Layup Shot", "2PT Field Goal", "Restricted Area", "Center(C)", "Less Than 8 ft.", 1, -18, 7, 1, 1, "20211217", "UTA", "SAS"], ["Shot Chart Detail", "0022100437", 44, 201144, "Mike Conley", 1610612762, "Utah Jazz", 1, 8, 23, "Missed Shot", "Hook Shot", "2PT Field Goal", "In The Paint (Non-RA)", "Center(C)", "Less Than 8 ft.", 6, 17, 64, 1, 0, "20211217", "UTA", "SAS"], ["Shot Chart Detail", "0022100437", 50, 203497, "Rudy Gobert", 1610612762, "Utah Jazz", 1, 8, 19, "Missed Shot", "Layup Shot", "2PT Field Goal", "Restricted Area", "Center(C)", "Less Than 8 ft.", 3, -26, 25, 1, 0, "20211217", "UTA", "SAS"], ["Shot Chart Detail", "0022100437", 46, 203497, "Rudy Gobert", 1610612762, "Utah Jazz", 1, 8, 19, "Missed Shot", "Layup Shot", "2PT Field Goal", "Restricted Area", "Center(C)", "Less Than 8 ft.", 3, -33, 20, 1, 0, "20211217", "UTA", "SAS"], ["Shot Chart Detail", "0022100437", 58, 201144, "Mike Conley", 1610612762, "Utah Jazz", 1, 8, 11, "Missed Shot", "Turnaround Jump Shot", "2PT Field Goal", "Mid-Range", "Right Side(R)", "8-16 ft.", 12, 116, 31, 1, 0, "20211217", "UTA", "SAS"], ["Shot Chart Detail", "0022100437", 63, 202711, "Bojan Bogdanovic", 1610612762, "Utah Jazz", 1, 7, 38, "Missed Shot", "Jump Shot", "3PT Field Goal", "Right Corner 3", "Right Side(R)", "24+ ft.", 22, 229, 20, 1, 0, "20211217", "UTA", "SAS"], ["Shot Chart Detail", "0022100437", 67, 203497, "Rudy Gobert", 1610612762, "Utah Jazz", 1, 7, 15, "Made Shot", "Cutting Dunk Shot", "2PT Field Goal", "Restricted Area", "Center(C)", "Less Than 8 ft.", 2, 6, 25, 1, 1, "20211217", "UTA", "SAS"], ["Shot Chart Detail", "0022100437", 89, 204060, "Joe Ingles", 1610612762, "Utah Jazz", 1, 6, 23, "Made Shot", "Driving Layup Shot", "2PT Field Goal", "In The Paint (Non-RA)", "Center(C)", "Less Than 8 ft.", 6, -50, 41, 1, 1, "20211217", "UTA", "SAS"], ["Shot Chart Detail", "0022100437", 96, 202355, "Hassan Whiteside", 1610612762, "Utah Jazz", 1, 5, 51, "Made Shot", "Cutting Layup Shot", "2PT Field Goal", "Restricted Area", "Center(C)", "Less Than 8 ft.", 3, 23, 25, 1, 1, "20211217", "UTA", "SAS"], ["Shot Chart Detail", "0022100437", 100, 202711, "Bojan Bogdanovic", 1610612762, "Utah Jazz", 1, 5, 18, "Missed Shot", "Driving Layup Shot", "2PT Field Goal", "In The Paint (Non-RA)", "Center(C)", "Less Than 8 ft.", 5, -37, 36, 1, 0, "20211217", "UTA", "SAS"], ["Shot Chart Detail", "0022100437", 104, 1628378, "Donovan Mitchell", 1610612762, "Utah Jazz", 1, 4, 49, "Missed Shot", "Jump Shot", "3PT Field Goal", "Right Corner 3", "Right Side(R)", "24+ ft.", 23, 224, 76, 1, 0, "20211217", "UTA", "SAS"], ["Shot Chart Detail", "0022100437", 108, 204060, "Joe Ingles", 1610612762, "Utah Jazz", 1, 4, 28, "Made Shot", "Pullup Jump shot", "3PT Field Goal", "Above the Break 3", "Right Side Center(RC)", "24+ ft.", 25, 141, 212, 1, 1, "20211217", "UTA", "SAS"], ["Shot Chart Detail", "0022100437", 120, 1628378, "Donovan Mitchell", 1610612762, "Utah Jazz", 1, 3, 56, "Made Shot", "Jump Shot", "3PT Field Goal", "Left Corner 3", "Left Side(L)", "24+ ft.", 23, -234, 22, 1, 1, "20211217", "UTA", "SAS"], ["Shot Chart Detail", "0022100437", 123, 200752, "Rudy Gay", 1610612762, "Utah Jazz", 1, 3, 15, "Made Shot", "Turnaround Fadeaway shot", "2PT Field Goal", "Mid-Range", "Right Side(R)", "8-16 ft.", 10, 102, 20, 1, 1, "20211217", "UTA", "SAS"], ["Shot Chart Detail", "0022100437", 125, 202355, "Hassan Whiteside", 1610612762, "Utah Jazz", 1, 2, 47, "Made Shot", "Hook Shot", "2PT Field Goal", "In The Paint (Non-RA)", "Center(C)", "Less Than 8 ft.", 4, -1, 41, 1, 1, "20211217", "UTA", "SAS"], ["Shot Chart Detail", "0022100437", 148, 200752, "Rudy Gay", 1610612762, "Utah Jazz", 1, 1, 35, "Missed Shot", "Fadeaway Jump Shot", "2PT Field Goal", "In The Paint (Non-RA)", "Left Side(L)", "8-16 ft.", 8, -80, 29, 1, 0, "20211217", "UTA", "SAS"], ["Shot Chart Detail", "0022100437", 152, 203903, "Jordan Clarkson", 1610612762, "Utah Jazz", 1, 1, 8, "Missed Shot", "Jump Shot", "3PT Field Goal", "Above the Break 3", "Left Side Center(LC)", "24+ ft.", 27, -183, 202, 1, 0, "20211217", "UTA", "SAS"], ["Shot Chart Detail", "0022100437", 154, 203497, "Rudy Gobert", 1610612762, "Utah Jazz", 1, 1, 3, "Made Shot", "Tip Dunk Shot", "2PT Field Goal", "Restricted Area", "Center(C)", "Less Than 8 ft.", 0, 0, 0, 1, 1, "20211217", "UTA", "SAS"], ["Shot Chart Detail", "0022100437", 160, 203903, "Jordan Clarkson", 1610612762, "Utah Jazz", 1, 0, 33, "Made Shot", "Jump Shot", "3PT Field Goal", "Above the Break 3", "Right Side Center(RC)", "24+ ft.", 26, 112, 235, 1, 1, "20211217", "UTA", "SAS"], ["Shot Chart Detail", "0022100437", 176, 203903, "Jordan Clarkson", 1610612762, "Utah Jazz", 2, 11, 40, "Made Shot", "Floating Jump shot", "2PT Field Goal", "In The Paint (Non-RA)", "Center(C)", "8-16 ft.", 9, 20, 88, 1, 1, "20211217", "UTA", "SAS"], ["Shot Chart Detail", "0022100437", 182, 204060, "Joe Ingles", 1610612762, "Utah Jazz", 2, 11, 6, "Missed Shot", "Pullup Jump shot", "3PT Field Goal", "Above the Break 3", "Left Side Center(LC)", "24+ ft.", 26, -147, 215, 1, 0, "20211217", "UTA", "SAS"], ["Shot Chart Detail", "0022100437", 189, 201144, "Mike Conley", 1610612762, "Utah Jazz", 2, 10, 30, "Made Shot", "Step Back Jump shot", "3PT Field Goal", "Above the Break 3", "Center(C)", "24+ ft.", 26, 55, 262, 1, 1, "20211217", "UTA", "SAS"], ["Shot Chart Detail", "0022100437", 193, 203903, "Jordan Clarkson", 1610612762, "Utah Jazz", 2, 10, 5, "Made Shot", "Driving Layup Shot", "2PT Field Goal", "Restricted Area", "Center(C)", "Less Than 8 ft.", 3, 23, 21, 1, 1, "20211217", "UTA", "SAS"], ["Shot Chart Detail", "0022100437", 206, 204060, "Joe Ingles", 1610612762, "Utah Jazz", 2, 9, 6, "Missed Shot", "Jump Shot", "3PT Field Goal", "Mid-Range", "Right Side(R)", "16-24 ft.", 22, 219, 70, 1, 0, "20211217", "UTA", "SAS"], ["Shot Chart Detail", "0022100437", 208, 203903, "Jordan Clarkson", 1610612762, "Utah Jazz", 2, 8, 53, "Made Shot", "Step Back Jump shot", "3PT Field Goal", "Above the Break 3", "Left Side Center(LC)", "24+ ft.", 25, -207, 151, 1, 1, "20211217", "UTA", "SAS"], ["Shot Chart Detail", "0022100437", 238, 1628378, "Donovan Mitchell", 1610612762, "Utah Jazz", 2, 7, 23, "Made Shot", "Jump Shot", "3PT Field Goal", "Above the Break 3", "Right Side Center(RC)", "24+ ft.", 27, 100, 253, 1, 1, "20211217", "UTA", "SAS"], ["Shot Chart Detail", "0022100437", 253, 203903, "Jordan Clarkson", 1610612762, "Utah Jazz", 2, 6, 42, "Missed Shot", "Step Back Jump shot", "3PT Field Goal", "Above the Break 3", "Left Side Center(LC)", "24+ ft.", 25, -116, 232, 1, 0, "20211217", "UTA", "SAS"], ["Shot Chart Detail", "0022100437", 276, 1628378, "Donovan Mitchell", 1610612762, "Utah Jazz", 2, 5, 32, "Made Shot", "Driving Layup Shot", "2PT Field Goal", "Restricted Area", "Center(C)", "Less Than 8 ft.", 3, -26, 23, 1, 1, "20211217", "UTA", "SAS"], ["Shot Chart Detail", "0022100437", 281, 1628378, "Donovan Mitchell", 1610612762, "Utah Jazz", 2, 5, 12, "Missed Shot", "Pullup Jump shot", "3PT Field Goal", "Above the Break 3", "Center(C)", "24+ ft.", 27, 18, 278, 1, 0, "20211217", "UTA", "SAS"], ["Shot Chart Detail", "0022100437", 285, 202355, "Hassan Whiteside", 1610612762, "Utah Jazz", 2, 4, 48, "Made Shot", "Floating Jump shot", "2PT Field Goal", "In The Paint (Non-RA)", "Center(C)", "Less Than 8 ft.", 4, 0, 47, 1, 1, "20211217", "UTA", "SAS"], ["Shot Chart Detail", "0022100437", 299, 203903, "Jordan Clarkson", 1610612762, "Utah Jazz", 2, 4, 20, "Missed Shot", "Pullup Jump shot", "3PT Field Goal", "Above the Break 3", "Left Side Center(LC)", "24+ ft.", 25, -190, 176, 1, 0, "20211217", "UTA", "SAS"], ["Shot Chart Detail", "0022100437", 301, 202711, "Bojan Bogdanovic", 1610612762, "Utah Jazz", 2, 4, 17, "Missed Shot", "Turnaround Fadeaway shot", "2PT Field Goal", "In The Paint (Non-RA)", "Center(C)", "8-16 ft.", 8, -2, 88, 1, 0, "20211217", "UTA", "SAS"], ["Shot Chart Detail", "0022100437", 314, 1628378, "Donovan Mitchell", 1610612762, "Utah Jazz", 2, 3, 54, "Made Shot", "Driving Layup Shot", "2PT Field Goal", "Restricted Area", "Center(C)", "Less Than 8 ft.", 2, 21, 13, 1, 1, "20211217", "UTA", "SAS"], ["Shot Chart Detail", "0022100437", 324, 202711, "Bojan Bogdanovic", 1610612762, "Utah Jazz", 2, 3, 8, "Missed Shot", "Step Back Jump shot", "3PT Field Goal", "Above the Break 3", "Left Side Center(LC)", "24+ ft.", 25, -141, 217, 1, 0, "20211217", "UTA", "SAS"], ["Shot Chart Detail", "0022100437", 326, 201144, "Mike Conley", 1610612762, "Utah Jazz", 2, 2, 58, "Made Shot", "Fadeaway Jump Shot", "2PT Field Goal", "In The Paint (Non-RA)", "Center(C)", "Less Than 8 ft.", 6, 37, 49, 1, 1, "20211217", "UTA", "SAS"], ["Shot Chart Detail", "0022100437", 335, 1626220, "Royce O'Neale", 1610612762, "Utah Jazz", 2, 2, 18, "Missed Shot", "Driving Layup Shot", "2PT Field Goal", "Restricted Area", "Center(C)", "Less Than 8 ft.", 3, -31, 22, 1, 0, "20211217", "UTA", "SAS"], ["Shot Chart Detail", "0022100437", 345, 1626220, "Royce O'Neale", 1610612762, "Utah Jazz", 2, 1, 51, "Made Shot", "Jump Shot", "3PT Field Goal", "Above the Break 3", "Right Side Center(RC)", "24+ ft.", 28, 153, 241, 1, 1, "20211217", "UTA", "SAS"], ["Shot Chart Detail", "0022100437", 352, 203497, "Rudy Gobert", 1610612762, "Utah Jazz", 2, 1, 13, "Made Shot", "Cutting Dunk Shot", "2PT Field Goal", "Restricted Area", "Center(C)", "Less Than 8 ft.", 2, -18, 20, 1, 1, "20211217", "UTA", "SAS"], ["Shot Chart Detail", "0022100437", 356, 1628378, "Donovan Mitchell", 1610612762, "Utah Jazz", 2, 0, 52, "Missed Shot", "Jump Shot", "3PT Field Goal", "Above the Break 3", "Center(C)", "24+ ft.", 29, -39, 289, 1, 0, "20211217", "UTA", "SAS"], ["Shot Chart Detail", "0022100437", 358, 1628378, "Donovan Mitchell", 1610612762, "Utah Jazz", 2, 0, 36, "Made Shot", "Step Back Jump shot", "3PT Field Goal", "Above the Break 3", "Left Side Center(LC)", "24+ ft.", 32, -237, 216, 1, 1, "20211217", "UTA", "SAS"], ["Shot Chart Detail", "0022100437", 362, 1628378, "Donovan Mitchell", 1610612762, "Utah Jazz", 2, 0, 3, "Missed Shot", "Jump Shot", "3PT Field Goal", "Above the Break 3", "Left Side Center(LC)", "24+ ft.", 29, -217, 196, 1, 0, "20211217", "UTA", "SAS"], ["Shot Chart Detail", "0022100437", 372, 1626220, "Royce O'Neale", 1610612762, "Utah Jazz", 3, 11, 48, "Made Shot", "Driving Floating Jump Shot", "2PT Field Goal", "In The Paint (Non-RA)", "Center(C)", "Less Than 8 ft.", 4, 17, 46, 1, 1, "20211217", "UTA", "SAS"], ["Shot Chart Detail", "0022100437", 376, 1626220, "Royce O'Neale", 1610612762, "Utah Jazz", 3, 11, 21, "Missed Shot", "Jump Shot", "3PT Field Goal", "Above the Break 3", "Center(C)", "24+ ft.", 25, -21, 256, 1, 0, "20211217", "UTA", "SAS"], ["Shot Chart Detail", "0022100437", 379, 202711, "Bojan Bogdanovic", 1610612762, "Utah Jazz", 3, 10, 50, "Missed Shot", "Driving Floating Bank Jump Shot", "2PT Field Goal", "In The Paint (Non-RA)", "Center(C)", "Less Than 8 ft.", 4, 37, 16, 1, 0, "20211217", "UTA", "SAS"], ["Shot Chart Detail", "0022100437", 382, 201144, "Mike Conley", 1610612762, "Utah Jazz", 3, 10, 24, "Missed Shot", "Floating Jump shot", "2PT Field Goal", "In The Paint (Non-RA)", "Right Side(R)", "8-16 ft.", 11, 71, 95, 1, 0, "20211217", "UTA", "SAS"], ["Shot Chart Detail", "0022100437", 391, 203497, "Rudy Gobert", 1610612762, "Utah Jazz", 3, 9, 55, "Made Shot", "Cutting Dunk Shot", "2PT Field Goal", "Restricted Area", "Center(C)", "Less Than 8 ft.", 1, -9, 9, 1, 1, "20211217", "UTA", "SAS"], ["Shot Chart Detail", "0022100437", 395, 1628378, "Donovan Mitchell", 1610612762, "Utah Jazz", 3, 9, 28, "Missed Shot", "Driving Layup Shot", "2PT Field Goal", "In The Paint (Non-RA)", "Center(C)", "Less Than 8 ft.", 5, 48, 24, 1, 0, "20211217", "UTA", "SAS"], ["Shot Chart Detail", "0022100437", 401, 1628378, "Donovan Mitchell", 1610612762, "Utah Jazz", 3, 9, 18, "Made Shot", "Driving Layup Shot", "2PT Field Goal", "Restricted Area", "Center(C)", "Less Than 8 ft.", 3, 37, 13, 1, 1, "20211217", "UTA", "SAS"], ["Shot Chart Detail", "0022100437", 404, 1628378, "Donovan Mitchell", 1610612762, "Utah Jazz", 3, 8, 53, "Missed Shot", "Step Back Jump shot", "2PT Field Goal", "Mid-Range", "Left Side Center(LC)", "16-24 ft.", 17, -105, 145, 1, 0, "20211217", "UTA", "SAS"], ["Shot Chart Detail", "0022100437", 408, 201144, "Mike Conley", 1610612762, "Utah Jazz", 3, 8, 38, "Missed Shot", "Step Back Jump shot", "3PT Field Goal", "Above the Break 3", "Right Side Center(RC)", "24+ ft.", 25, 192, 171, 1, 0, "20211217", "UTA", "SAS"], ["Shot Chart Detail", "0022100437", 413, 202711, "Bojan Bogdanovic", 1610612762, "Utah Jazz", 3, 8, 11, "Made Shot", "Driving Layup Shot", "2PT Field Goal", "Restricted Area", "Center(C)", "Less Than 8 ft.", 3, 33, 15, 1, 1, "20211217", "UTA", "SAS"], ["Shot Chart Detail", "0022100437", 416, 1626220, "Royce O'Neale", 1610612762, "Utah Jazz", 3, 7, 43, "Made Shot", "Layup Shot", "2PT Field Goal", "Restricted Area", "Center(C)", "Less Than 8 ft.", 2, -25, 5, 1, 1, "20211217", "UTA", "SAS"], ["Shot Chart Detail", "0022100437", 420, 201144, "Mike Conley", 1610612762, "Utah Jazz", 3, 7, 16, "Missed Shot", "Jump Shot", "3PT Field Goal", "Right Corner 3", "Right Side(R)", "24+ ft.", 24, 244, 6, 1, 0, "20211217", "UTA", "SAS"], ["Shot Chart Detail", "0022100437", 424, 1628378, "Donovan Mitchell", 1610612762, "Utah Jazz", 3, 6, 55, "Missed Shot", "Jump Shot", "3PT Field Goal", "Above the Break 3", "Center(C)", "24+ ft.", 25, 38, 252, 1, 0, "20211217", "UTA", "SAS"], ["Shot Chart Detail", "0022100437", 434, 202711, "Bojan Bogdanovic", 1610612762, "Utah Jazz", 3, 6, 22, "Made Shot", "Driving Layup Shot", "2PT Field Goal", "Restricted Area", "Center(C)", "Less Than 8 ft.", 2, 27, 13, 1, 1, "20211217", "UTA", "SAS"], ["Shot Chart Detail", "0022100437", 436, 1628378, "Donovan Mitchell", 1610612762, "Utah Jazz", 3, 6, 0, "Missed Shot", "Jump Shot", "3PT Field Goal", "Above the Break 3", "Right Side Center(RC)", "24+ ft.", 25, 168, 192, 1, 0, "20211217", "UTA", "SAS"], ["Shot Chart Detail", "0022100437", 438, 202711, "Bojan Bogdanovic", 1610612762, "Utah Jazz", 3, 5, 56, "Made Shot", "Jump Shot", "3PT Field Goal", "Above the Break 3", "Left Side Center(LC)", "24+ ft.", 25, -121, 219, 1, 1, "20211217", "UTA", "SAS"], ["Shot Chart Detail", "0022100437", 442, 202355, "Hassan Whiteside", 1610612762, "Utah Jazz", 3, 5, 29, "Made Shot", "Floating Jump shot", "2PT Field Goal", "In The Paint (Non-RA)", "Center(C)", "Less Than 8 ft.", 5, 45, 26, 1, 1, "20211217", "UTA", "SAS"], ["Shot Chart Detail", "0022100437", 453, 1628378, "Donovan Mitchell", 1610612762, "Utah Jazz", 3, 4, 30, "Missed Shot", "Driving Layup Shot", "2PT Field Goal", "In The Paint (Non-RA)", "Center(C)", "Less Than 8 ft.", 5, 48, 19, 1, 0, "20211217", "UTA", "SAS"], ["Shot Chart Detail", "0022100437", 483, 1628378, "Donovan Mitchell", 1610612762, "Utah Jazz", 3, 3, 12, "Missed Shot", "Pullup Jump shot", "3PT Field Goal", "Above the Break 3", "Right Side Center(RC)", "24+ ft.", 26, 143, 220, 1, 0, "20211217", "UTA", "SAS"], ["Shot Chart Detail", "0022100437", 498, 200752, "Rudy Gay", 1610612762, "Utah Jazz", 3, 2, 34, "Missed Shot", "Jump Shot", "3PT Field Goal", "Above the Break 3", "Left Side Center(LC)", "24+ ft.", 28, -161, 234, 1, 0, "20211217", "UTA", "SAS"], ["Shot Chart Detail", "0022100437", 501, 203497, "Rudy Gobert", 1610612762, "Utah Jazz", 3, 2, 0, "Missed Shot", "Alley Oop Layup shot", "2PT Field Goal", "In The Paint (Non-RA)", "Center(C)", "Less Than 8 ft.", 4, 38, 20, 1, 0, "20211217", "UTA", "SAS"], ["Shot Chart Detail", "0022100437", 510, 201144, "Mike Conley", 1610612762, "Utah Jazz", 3, 1, 0, "Made Shot", "Pullup Jump shot", "3PT Field Goal", "Above the Break 3", "Center(C)", "24+ ft.", 25, 70, 241, 1, 1, "20211217", "UTA", "SAS"], ["Shot Chart Detail", "0022100437", 520, 201144, "Mike Conley", 1610612762, "Utah Jazz", 3, 0, 36, "Missed Shot", "Driving Layup Shot", "2PT Field Goal", "Restricted Area", "Center(C)", "Less Than 8 ft.", 2, -17, 13, 1, 0, "20211217", "UTA", "SAS"], ["Shot Chart Detail", "0022100437", 524, 203903, "Jordan Clarkson", 1610612762, "Utah Jazz", 3, 0, 8, "Missed Shot", "Step Back Jump shot", "3PT Field Goal", "Above the Break 3", "Center(C)", "24+ ft.", 24, -66, 234, 1, 0, "20211217", "UTA", "SAS"], ["Shot Chart Detail", "0022100437", 547, 203903, "Jordan Clarkson", 1610612762, "Utah Jazz", 4, 10, 53, "Made Shot", "Turnaround Jump Shot", "2PT Field Goal", "Restricted Area", "Center(C)", "Less Than 8 ft.", 3, -22, 21, 1, 1, "20211217", "UTA", "SAS"], ["Shot Chart Detail", "0022100437", 550, 203903, "Jordan Clarkson", 1610612762, "Utah Jazz", 4, 10, 24, "Missed Shot", "Turnaround Fadeaway Bank Jump Shot", "2PT Field Goal", "In The Paint (Non-RA)", "Center(C)", "Less Than 8 ft.", 5, -20, 51, 1, 0, "20211217", "UTA", "SAS"], ["Shot Chart Detail", "0022100437", 554, 203903, "Jordan Clarkson", 1610612762, "Utah Jazz", 4, 9, 39, "Made Shot", "Step Back Jump shot", "3PT Field Goal", "Above the Break 3", "Left Side Center(LC)", "24+ ft.", 25, -170, 192, 1, 1, "20211217", "UTA", "SAS"], ["Shot Chart Detail", "0022100437", 556, 204060, "Joe Ingles", 1610612762, "Utah Jazz", 4, 9, 3, "Missed Shot", "Step Back Jump shot", "2PT Field Goal", "Mid-Range", "Right Side(R)", "16-24 ft.", 23, 212, 100, 1, 0, "20211217", "UTA", "SAS"], ["Shot Chart Detail", "0022100437", 568, 202355, "Hassan Whiteside", 1610612762, "Utah Jazz", 4, 8, 33, "Missed Shot", "Floating Jump shot", "2PT Field Goal", "In The Paint (Non-RA)", "Center(C)", "Less Than 8 ft.", 7, 2, 72, 1, 0, "20211217", "UTA", "SAS"], ["Shot Chart Detail", "0022100437", 570, 203903, "Jordan Clarkson", 1610612762, "Utah Jazz", 4, 8, 18, "Made Shot", "Driving Layup Shot", "2PT Field Goal", "In The Paint (Non-RA)", "Center(C)", "Less Than 8 ft.", 6, 60, 34, 1, 1, "20211217", "UTA", "SAS"], ["Shot Chart Detail", "0022100437", 572, 201144, "Mike Conley", 1610612762, "Utah Jazz", 4, 7, 44, "Missed Shot", "Jump Shot", "3PT Field Goal", "Above the Break 3", "Right Side Center(RC)", "24+ ft.", 25, 83, 236, 1, 0, "20211217", "UTA", "SAS"], ["Shot Chart Detail", "0022100437", 583, 203903, "Jordan Clarkson", 1610612762, "Utah Jazz", 4, 7, 20, "Missed Shot", "Floating Jump shot", "2PT Field Goal", "Mid-Range", "Right Side(R)", "8-16 ft.", 11, 107, 29, 1, 0, "20211217", "UTA", "SAS"], ["Shot Chart Detail", "0022100437", 605, 1628378, "Donovan Mitchell", 1610612762, "Utah Jazz", 4, 6, 17, "Missed Shot", "Driving Layup Shot", "2PT Field Goal", "Restricted Area", "Center(C)", "Less Than 8 ft.", 2, -17, 13, 1, 0, "20211217", "UTA", "SAS"], ["Shot Chart Detail", "0022100437", 610, 203903, "Jordan Clarkson", 1610612762, "Utah Jazz", 4, 5, 53, "Missed Shot", "Layup Shot", "2PT Field Goal", "Restricted Area", "Center(C)", "Less Than 8 ft.", 3, 32, 19, 1, 0, "20211217", "UTA", "SAS"], ["Shot Chart Detail", "0022100437", 614, 202711, "Bojan Bogdanovic", 1610612762, "Utah Jazz", 4, 5, 35, "Missed Shot", "Driving Layup Shot", "2PT Field Goal", "Restricted Area", "Center(C)", "Less Than 8 ft.", 3, 38, 11, 1, 0, "20211217", "UTA", "SAS"], ["Shot Chart Detail", "0022100437", 628, 203903, "Jordan Clarkson", 1610612762, "Utah Jazz", 4, 5, 7, "Made Shot", "Driving Floating Jump Shot", "2PT Field Goal", "In The Paint (Non-RA)", "Center(C)", "Less Than 8 ft.", 5, 0, 52, 1, 1, "20211217", "UTA", "SAS"], ["Shot Chart Detail", "0022100437", 633, 201144, "Mike Conley", 1610612762, "Utah Jazz", 4, 4, 29, "Made Shot", "Jump Shot", "3PT Field Goal", "Left Corner 3", "Left Side(L)", "24+ ft.", 23, -223, 71, 1, 1, "20211217", "UTA", "SAS"], ["Shot Chart Detail", "0022100437", 637, 202711, "Bojan Bogdanovic", 1610612762, "Utah Jazz", 4, 3, 57, "Made Shot", "Driving Layup Shot", "2PT Field Goal", "In The Paint (Non-RA)", "Center(C)", "Less Than 8 ft.", 4, 40, 20, 1, 1, "20211217", "UTA", "SAS"], ["Shot Chart Detail", "0022100437", 641, 201144, "Mike Conley", 1610612762, "Utah Jazz", 4, 3, 23, "Made Shot", "Pullup Jump shot", "3PT Field Goal", "Above the Break 3", "Right Side Center(RC)", "24+ ft.", 24, 217, 114, 1, 1, "20211217", "UTA", "SAS"], ["Shot Chart Detail", "0022100437", 643, 201144, "Mike Conley", 1610612762, "Utah Jazz", 4, 2, 47, "Missed Shot", "Step Back Jump shot", "3PT Field Goal", "Right Corner 3", "Right Side(R)", "24+ ft.", 23, 237, 25, 1, 0, "20211217", "UTA", "SAS"], ["Shot Chart Detail", "0022100437", 645, 201144, "Mike Conley", 1610612762, "Utah Jazz", 4, 2, 41, "Missed Shot", "Jump Shot", "3PT Field Goal", "Right Corner 3", "Right Side(R)", "24+ ft.", 23, 235, 17, 1, 0, "20211217", "UTA", "SAS"], ["Shot Chart Detail", "0022100437", 653, 1628378, "Donovan Mitchell", 1610612762, "Utah Jazz", 4, 2, 6, "Made Shot", "Driving Layup Shot", "2PT Field Goal", "Restricted Area", "Center(C)", "Less Than 8 ft.", 2, 29, 6, 1, 1, "20211217", "UTA", "SAS"], ["Shot Chart Detail", "0022100437", 656, 201144, "Mike Conley", 1610612762, "Utah Jazz", 4, 1, 33, "Made Shot", "Driving Floating Jump Shot", "2PT Field Goal", "In The Paint (Non-RA)", "Center(C)", "8-16 ft.", 10, 34, 95, 1, 1, "20211217", "UTA", "SAS"], ["Shot Chart Detail", "0022100437", 663, 1628378, "Donovan Mitchell", 1610612762, "Utah Jazz", 4, 1, 1, "Made Shot", "Driving Layup Shot", "2PT Field Goal", "Restricted Area", "Center(C)", "Less Than 8 ft.", 2, 5, 26, 1, 1, "20211217", "UTA", "SAS"], ["Shot Chart Detail", "0022100437", 669, 1628378, "Donovan Mitchell", 1610612762, "Utah Jazz", 4, 0, 33, "Made Shot", "Turnaround Jump Shot", "2PT Field Goal", "In The Paint (Non-RA)", "Center(C)", "8-16 ft.", 12, 4, 120, 1, 1, "20211217", "UTA", "SAS"], ["Shot Chart Detail", "0022100437", 674, 1628378, "Donovan Mitchell", 1610612762, "Utah Jazz", 4, 0, 4, "Missed Shot", "Driving Layup Shot", "2PT Field Goal", "In The Paint (Non-RA)", "Center(C)", "Less Than 8 ft.", 4, 36, 30, 1, 0, "20211217", "UTA", "SAS"], ["Shot Chart Detail", "0022100437", 688, 1628378, "Donovan Mitchell", 1610612762, "Utah Jazz", 4, 0, 0, "Missed Shot", "Jump Shot", "3PT Field Goal", "Above the Break 3", "Right Side Center(RC)", "24+ ft.", 30, 196, 234, 1, 0, "20211217", "UTA", "SAS"]]}, {"name": "LeagueAverages", "headers": ["GRID_TYPE", "SHOT_ZONE_BASIC", "SHOT_ZONE_AREA", "SHOT_ZONE_RANGE", "FGA", "FGM", "FG_PCT"], "rowSet": [["League Averages", "Above the Break 3", "Back Court(BC)", "Back Court Shot", 35, 4, 0.114], ["League Averages", "Above the Break 3", "Center(C)", "24+ ft.", 16368, 5613, 0.343], ["League Averages", "Above the Break 3", "Left Side Center(LC)", "24+ ft.", 24924, 8511, 0.341], ["League Averages", "Above the Break 3", "Right Side Center(RC)", "24+ ft.", 23120, 8171, 0.353], ["League Averages", "Backcourt", "Back Court(BC)", "Back Court Shot", 440, 11, 0.025], ["League Averages", "In The Paint (Non-RA)", "Center(C)", "8-16 ft.", 11777, 5228, 0.444], ["League Averages", "In The Paint (Non-RA)", "Center(C)", "Less Than 8 ft.", 23351, 9813, 0.42], ["League Averages", "In The Paint (Non-RA)", "Left Side(L)", "8-16 ft.", 2197, 949, 0.432], ["League Averages", "In The Paint (Non-RA)", "Right Side(R)", "8-16 ft.", 2343, 1000, 0.427], ["League Averages", "Left Corner 3", "Left Side(L)", "24+ ft.", 11377, 4371, 0.384], ["League Averages", "Mid-Range", "Center(C)", "8-16 ft.", 2088, 921, 0.441], ["League Averages", "Mid-Range", "Center(C)", "16-24 ft.", 4165, 1743, 0.418], ["League Averages", "Mid-Range", "Left Side Center(LC)", "16-24 ft.", 3972, 1632, 0.411], ["League Averages", "Mid-Range", "Left Side(L)", "8-16 ft.", 5014, 2023, 0.403], ["League Averages", "Mid-Range", "Left Side(L)", "16-24 ft.", 1680, 613, 0.365], ["League Averages", "Mid-Range", "Right Side Center(RC)", "16-24 ft.", 4043, 1575, 0.39], ["League Averages", "Mid-Range", "Right Side(R)", "16-24 ft.", 1609, 614, 0.382], ["League Averages", "Mid-Range", "Right Side(R)", "8-16 ft.", 5141, 2143, 0.417], ["League Averages", "Restricted Area", "Center(C)", "Less Than 8 ft.", 62987, 41140, 0.653], ["League Averages", "Right Corner 3", "Right Side(R)", "24+ ft.", 10091, 3855, 0.382]]}]}