{"resource": "shotchartdetail", "parameters": {"LeagueID": "00", "Season": "2021-22", "SeasonType": "Regular Season", "TeamID": 1610612745, "PlayerID": 0, "GameID": "0022100395", "Outcome": null, "Location": null, "Month": 0, "SeasonSegment": null, "DateFrom": null, "DateTo": null, "OpponentTeamID": 0, "VsConference": null, "VsDivision": null, "Position": null, "RookieYear": null, "GameSegment": null, "Period": 0, "LastNGames": 0, "ClutchTime": null, "AheadBehind": null, "PointDiff": null, "RangeType": null, "StartPeriod": null, "EndPeriod": null, "StartRange": null, "EndRange": null, "ContextFilter": "", "ContextMeasure": "FG_PCT"}, "resultSets": [{"name": "Shot_Chart_Detail", "headers": ["GRID_TYPE", "GAME_ID", "GAME_EVENT_ID", "PLAYER_ID", "PLAYER_NAME", "TEAM_ID", "TEAM_NAME", "PERIOD", "MINUTES_REMAINING", "SECONDS_REMAINING", "EVENT_TYPE", "ACTION_TYPE", "SHOT_TYPE", "SHOT_ZONE_BASIC", "SHOT_ZONE_AREA", "SHOT_ZONE_RANGE", "SHOT_DISTANCE", "LOC_X", "LOC_Y", "SHOT_ATTEMPTED_FLAG", "SHOT_MADE_FLAG", "GAME_DATE", "HTM", "VTM"], "rowSet": [["Shot Chart Detail", "0022100395", 15, 1630256, "Jae'Sean Tate", 1610612745, "Houston Rockets", 1, 11, 14, "Missed Shot", "Jump Shot", "3PT Field Goal", "Above the Break 3", "Left Side Center(LC)", "24+ ft.", 26, -146, 216, 1, 0, "20211211", "MEM", "HOU"], ["Shot Chart Detail", "0022100395", 30, 1629726, "Garrison Mathews", 1610612745, "Houston Rockets", 1, 9, 54, "Missed Shot", "Jump Shot", "3PT Field Goal", "Above the Break 3", "Center(C)", "24+ ft.", 26, 72, 252, 1, 0, "20211211", "MEM", "HOU"], ["Shot Chart Detail", "0022100395", 37, 1629726, "Garrison Mathews", 1610612745, "Houston Rockets", 1, 9, 3, "Missed Shot", "Pullup Jump shot", "3PT Field Goal", "Above the Break 3", "Center(C)", "24+ ft.", 26, 50, 258, 1, 0, "20211211", "MEM", "HOU"], ["Shot Chart Detail", "0022100395", 42, 1630256, "Jae'Sean Tate", 1610612745, "Houston Rockets", 1, 8, 39, "Missed Shot", "Driving Hook Shot", "2PT Field Goal", "Restricted Area", "Center(C)", "Less Than 8 ft.", 2, -26, 8, 1, 0, "20211211", "MEM", "HOU"], ["Shot Chart Detail", "0022100395", 47, 201571, "D.J. Augustin", 1610612745, "Houston Rockets", 1, 8, 21, "Made Shot", "Jump Shot", "3PT Field Goal", "Above the Break 3", "Left Side Center(LC)", "24+ ft.", 25, -168, 197, 1, 1, "20211211", "MEM", "HOU"], ["Shot Chart Detail", "0022100395", 63, 1628464, "Daniel Theis", 1610612745, "Houston Rockets", 1, 6, 55, "Missed Shot", "Pullup Jump shot", "2PT Field Goal", "In The Paint (Non-RA)", "Center(C)", "8-16 ft.", 12, -1, 120, 1, 0, "20211211", "MEM", "HOU"], ["Shot Chart Detail", "0022100395", 77, 1628464, "Daniel Theis", 1610612745, "Houston Rockets", 1, 6, 12, "Made Shot", "Cutting Finger Roll Layup Shot", "2PT Field Goal", "Restricted Area", "Center(C)", "Less Than 8 ft.", 0, 1, 4, 1, 1, "20211211", "MEM", "HOU"], ["Shot Chart Detail", "0022100395", 96, 1629717, "Armoni Brooks", 1610612745, "Houston Rockets", 1, 4, 45, "Made Shot", "Driving Floating Jump Shot", "2PT Field Goal", "In The Paint (Non-RA)", "Center(C)", "Less Than 8 ft.", 7, 21, 67, 1, 1, "20211211", "MEM", "HOU"], ["Shot Chart Detail", "0022100395", 100, 1630578, "Alperen Sengun", 1610612745, "Houston Rockets", 1, 4, 23, "Made Shot", "Cutting Layup Shot", "2PT Field Goal", "Restricted Area", "Center(C)", "Less Than 8 ft.", 1, -11, 1, 1, 1, "20211211", "MEM", "HOU"], ["Shot Chart Detail", "0022100395", 111, 1629717, "Armoni Brooks", 1610612745, "Houston Rockets", 1, 3, 45, "Made Shot", "Jump Shot", "3PT Field Goal", "Above the Break 3", "Left Side Center(LC)", "24+ ft.", 26, -115, 235, 1, 1, "20211211", "MEM", "HOU"], ["Shot Chart Detail", "0022100395", 118, 1626174, "Christian Wood", 1610612745, "Houston Rockets", 1, 3, 0, "Made Shot", "Alley Oop Dunk Shot", "2PT Field Goal", "Restricted Area", "Center(C)", "Less Than 8 ft.", 0, -5, 1, 1, 1, "20211211", "MEM", "HOU"], ["Shot Chart Detail", "0022100395", 130, 1630528, "Josh Christopher", 1610612745, "Houston Rockets", 1, 2, 39, "Made Shot", "Jump Shot", "3PT Field Goal", "Above the Break 3", "Left Side Center(LC)", "24+ ft.", 27, -97, 252, 1, 1, "20211211", "MEM", "HOU"], ["Shot Chart Detail", "0022100395", 134, 1629717, "Armoni Brooks", 1610612745, "Houston Rockets", 1, 1, 48, "Made Shot", "Pullup Jump shot", "3PT Field Goal", "Above the Break 3", "Left Side Center(LC)", "24+ ft.", 27, -184, 207, 1, 1, "20211211", "MEM", "HOU"], ["Shot Chart Detail", "0022100395", 141, 1630256, "Jae'Sean Tate", 1610612745, "Houston Rockets", 1, 0, 58, "Made Shot", "Tip Dunk Shot", "2PT Field Goal", "Restricted Area", "Center(C)", "Less Than 8 ft.", 0, 0, 0, 1, 1, "20211211", "MEM", "HOU"], ["Shot Chart Detail", "0022100395", 139, 1630578, "Alperen Sengun", 1610612745, "Houston Rockets", 1, 0, 58, "Missed Shot", "Driving Finger Roll Layup Shot", "2PT Field Goal", "Restricted Area", "Center(C)", "Less Than 8 ft.", 1, -12, 11, 1, 0, "20211211", "MEM", "HOU"], ["Shot Chart Detail", "0022100395", 145, 1630578, "Alperen Sengun", 1610612745, "Houston Rockets", 1, 0, 28, "Missed Shot", "Driving Layup Shot", "2PT Field Goal", "Restricted Area", "Center(C)", "Less Than 8 ft.", 3, -26, 20, 1, 0, "20211211", "MEM", "HOU"], ["Shot Chart Detail", "0022100395", 163, 1630528, "Josh Christopher", 1610612745, "Houston Rockets", 2, 11, 36, "Missed Shot", "Pullup Jump shot", "2PT Field Goal", "Mid-Range", "Right Side Center(RC)", "16-24 ft.", 21, 98, 188, 1, 0, "20211211", "MEM", "HOU"], ["Shot Chart Detail", "0022100395", 167, 1629717, "Armoni Brooks", 1610612745, "Houston Rockets", 2, 11, 5, "Missed Shot", "Pullup Jump shot", "3PT Field Goal", "Above the Break 3", "Right Side Center(RC)", "24+ ft.", 27, 138, 243, 1, 0, "20211211", "MEM", "HOU"], ["Shot Chart Detail", "0022100395", 170, 1630231, "Kenyon Martin Jr.", 1610612745, "Houston Rockets", 2, 10, 56, "Made Shot", "Cutting Dunk Shot", "2PT Field Goal", "Restricted Area", "Center(C)", "Less Than 8 ft.", 1, -1, 11, 1, 1, "20211211", "MEM", "HOU"], ["Shot Chart Detail", "0022100395", 174, 1630528, "Josh Christopher", 1610612745, "Houston Rockets", 2, 10, 19, "Made Shot", "Driving Finger Roll Layup Shot", "2PT Field Goal", "Restricted Area", "Center(C)", "Less Than 8 ft.", 1, -11, 6, 1, 1, "20211211", "MEM", "HOU"], ["Shot Chart Detail", "0022100395", 180, 1630578, "Alperen Sengun", 1610612745, "Houston Rockets", 2, 9, 43, "Missed Shot", "Driving Layup Shot", "2PT Field Goal", "Restricted Area", "Center(C)", "Less Than 8 ft.", 2, 12, 16, 1, 0, "20211211", "MEM", "HOU"], ["Shot Chart Detail", "0022100395", 191, 1630528, "Josh Christopher", 1610612745, "Houston Rockets", 2, 9, 17, "Missed Shot", "Driving Floating Jump Shot", "2PT Field Goal", "Restricted Area", "Center(C)", "Less Than 8 ft.", 2, 20, 4, 1, 0, "20211211", "MEM", "HOU"], ["Shot Chart Detail", "0022100395", 201, 1629726, "Garrison Mathews", 1610612745, "Houston Rockets", 2, 8, 40, "Missed Shot", "Step Back Jump shot", "3PT Field Goal", "Left Corner 3", "Left Side(L)", "24+ ft.", 23, -235, 15, 1, 0, "20211211", "MEM", "HOU"], ["Shot Chart Detail", "0022100395", 203, 1630528, "Josh Christopher", 1610612745, "Houston Rockets", 2, 8, 35, "Made Shot", "Jump Shot", "3PT Field Goal", "Above the Break 3", "Right Side Center(RC)", "24+ ft.", 24, 192, 159, 1, 1, "20211211", "MEM", "HOU"], ["Shot Chart Detail", "0022100395", 213, 1629717, "Armoni Brooks", 1610612745, "Houston Rockets", 2, 8, 2, "Missed Shot", "Pullup Jump shot", "3PT Field Goal", "Above the Break 3", "Center(C)", "24+ ft.", 27, -74, 262, 1, 0, "20211211", "MEM", "HOU"], ["Shot Chart Detail", "0022100395", 226, 1626174, "Christian Wood", 1610612745, "Houston Rockets", 2, 7, 23, "Missed Shot", "Jump Shot", "3PT Field Goal", "Above the Break 3", "Left Side Center(LC)", "24+ ft.", 26, -98, 243, 1, 0, "20211211", "MEM", "HOU"], ["Shot Chart Detail", "0022100395", 229, 1626174, "Christian Wood", 1610612745, "Houston Rockets", 2, 6, 56, "Made Shot", "Cutting Layup Shot", "2PT Field Goal", "Restricted Area", "Center(C)", "Less Than 8 ft.", 2, 20, 6, 1, 1, "20211211", "MEM", "HOU"], ["Shot Chart Detail", "0022100395", 233, 1626174, "Christian Wood", 1610612745, "Houston Rockets", 2, 6, 26, "Missed Shot", "Step Back Jump shot", "2PT Field Goal", "Mid-Range", "Right Side Center(RC)", "16-24 ft.", 22, 96, 209, 1, 0, "20211211", "MEM", "HOU"], ["Shot Chart Detail", "0022100395", 237, 1630528, "Josh Christopher", 1610612745, "Houston Rockets", 2, 6, 9, "Missed Shot", "Jump Shot", "3PT Field Goal", "Right Corner 3", "Right Side(R)", "24+ ft.", 23, 223, 67, 1, 0, "20211211", "MEM", "HOU"], ["Shot Chart Detail", "0022100395", 251, 201571, "D.J. Augustin", 1610612745, "Houston Rockets", 2, 5, 29, "Missed Shot", "Pullup Jump shot", "2PT Field Goal", "In The Paint (Non-RA)", "Center(C)", "Less Than 8 ft.", 6, 60, 26, 1, 0, "20211211", "MEM", "HOU"], ["Shot Chart Detail", "0022100395", 255, 1629726, "Garrison Mathews", 1610612745, "Houston Rockets", 2, 4, 52, "Made Shot", "Driving Layup Shot", "2PT Field Goal", "Restricted Area", "Center(C)", "Less Than 8 ft.", 1, 0, 16, 1, 1, "20211211", "MEM", "HOU"], ["Shot Chart Detail", "0022100395", 266, 1630256, "Jae'Sean Tate", 1610612745, "Houston Rockets", 2, 4, 16, "Made Shot", "Layup Shot", "2PT Field Goal", "In The Paint (Non-RA)", "Center(C)", "Less Than 8 ft.", 5, -53, 17, 1, 1, "20211211", "MEM", "HOU"], ["Shot Chart Detail", "0022100395", 272, 1630256, "Jae'Sean Tate", 1610612745, "Houston Rockets", 2, 3, 32, "Missed Shot", "Turnaround Hook Shot", "2PT Field Goal", "In The Paint (Non-RA)", "Center(C)", "Less Than 8 ft.", 5, 39, 34, 1, 0, "20211211", "MEM", "HOU"], ["Shot Chart Detail", "0022100395", 278, 1629726, "Garrison Mathews", 1610612745, "Houston Rockets", 2, 2, 49, "Missed Shot", "Pullup Jump shot", "3PT Field Goal", "Above the Break 3", "Right Side Center(RC)", "24+ ft.", 25, 175, 181, 1, 0, "20211211", "MEM", "HOU"], ["Shot Chart Detail", "0022100395", 283, 1628464, "Daniel Theis", 1610612745, "Houston Rockets", 2, 2, 12, "Missed Shot", "Jump Shot", "3PT Field Goal", "Left Corner 3", "Left Side(L)", "24+ ft.", 22, -227, 17, 1, 0, "20211211", "MEM", "HOU"], ["Shot Chart Detail", "0022100395", 293, 1626174, "Christian Wood", 1610612745, "Houston Rockets", 2, 1, 50, "Made Shot", "Jump Shot", "3PT Field Goal", "Above the Break 3", "Right Side Center(RC)", "24+ ft.", 25, 113, 233, 1, 1, "20211211", "MEM", "HOU"], ["Shot Chart Detail", "0022100395", 301, 1629717, "Armoni Brooks", 1610612745, "Houston Rockets", 2, 1, 18, "Missed Shot", "Running Pull-Up Jump Shot", "3PT Field Goal", "Above the Break 3", "Right Side Center(RC)", "24+ ft.", 25, 151, 211, 1, 0, "20211211", "MEM", "HOU"], ["Shot Chart Detail", "0022100395", 305, 1626174, "Christian Wood", 1610612745, "Houston Rockets", 2, 0, 58, "Missed Shot", "Driving Floating Bank Jump Shot", "2PT Field Goal", "In The Paint (Non-RA)", "Center(C)", "Less Than 8 ft.", 7, -48, 57, 1, 0, "20211211", "MEM", "HOU"], ["Shot Chart Detail", "0022100395", 316, 1628464, "Daniel Theis", 1610612745, "Houston Rockets", 2, 0, 19, "Made Shot", "Cutting Finger Roll Layup Shot", "2PT Field Goal", "Restricted Area", "Center(C)", "Less Than 8 ft.", 1, -15, 4, 1, 1, "20211211", "MEM", "HOU"], ["Shot Chart Detail", "0022100395", 326, 1629726, "Garrison Mathews", 1610612745, "Houston Rockets", 3, 11, 44, "Made Shot", "Pullup Jump shot", "3PT Field Goal", "Above the Break 3", "Left Side Center(LC)", "24+ ft.", 25, -137, 216, 1, 1, "20211211", "MEM", "HOU"], ["Shot Chart Detail", "0022100395", 339, 1626174, "Christian Wood", 1610612745, "Houston Rockets", 3, 10, 51, "Made Shot", "Running Finger Roll Layup Shot", "2PT Field Goal", "Restricted Area", "Center(C)", "Less Than 8 ft.", 0, 1, 9, 1, 1, "20211211", "MEM", "HOU"], ["Shot Chart Detail", "0022100395", 342, 1628464, "Daniel Theis", 1610612745, "Houston Rockets", 3, 10, 18, "Missed Shot", "Jump Shot", "3PT Field Goal", "Right Corner 3", "Right Side(R)", "24+ ft.", 23, 234, -6, 1, 0, "20211211", "MEM", "HOU"], ["Shot Chart Detail", "0022100395", 351, 1628464, "Daniel Theis", 1610612745, "Houston Rockets", 3, 9, 39, "Made Shot", "Cutting Dunk Shot", "2PT Field Goal", "Restricted Area", "Center(C)", "Less Than 8 ft.", 1, 0, 13, 1, 1, "20211211", "MEM", "HOU"], ["Shot Chart Detail", "0022100395", 357, 1628464, "Daniel Theis", 1610612745, "Houston Rockets", 3, 9, 5, "Missed Shot", "Jump Shot", "3PT Field Goal", "Above the Break 3", "Center(C)", "24+ ft.", 25, 15, 252, 1, 0, "20211211", "MEM", "HOU"], ["Shot Chart Detail", "0022100395", 361, 201571, "D.J. Augustin", 1610612745, "Houston Rockets", 3, 8, 46, "Missed Shot", "Jump Shot", "3PT Field Goal", "Above the Break 3", "Right Side Center(RC)", "24+ ft.", 25, 116, 222, 1, 0, "20211211", "MEM", "HOU"], ["Shot Chart Detail", "0022100395", 365, 1630256, "Jae'Sean Tate", 1610612745, "Houston Rockets", 3, 8, 8, "Missed Shot", "Pullup Jump shot", "2PT Field Goal", "Mid-Range", "Left Side(L)", "8-16 ft.", 10, -92, 52, 1, 0, "20211211", "MEM", "HOU"], ["Shot Chart Detail", "0022100395", 375, 1630231, "Kenyon Martin Jr.", 1610612745, "Houston Rockets", 3, 7, 34, "Missed Shot", "Layup Shot", "2PT Field Goal", "Restricted Area", "Center(C)", "Less Than 8 ft.", 3, -26, 20, 1, 0, "20211211", "MEM", "HOU"], ["Shot Chart Detail", "0022100395", 395, 1629726, "Garrison Mathews", 1610612745, "Houston Rockets", 3, 6, 29, "Missed Shot", "Jump Shot", "3PT Field Goal", "Above the Break 3", "Center(C)", "24+ ft.", 25, 11, 258, 1, 0, "20211211", "MEM", "HOU"], ["Shot Chart Detail", "0022100395", 404, 201571, "D.J. Augustin", 1610612745, "Houston Rockets", 3, 6, 20, "Missed Shot", "Jump Shot", "3PT Field Goal", "Above the Break 3", "Left Side Center(LC)", "24+ ft.", 25, -120, 230, 1, 0, "20211211", "MEM", "HOU"], ["Shot Chart Detail", "0022100395", 408, 1630231, "Kenyon Martin Jr.", 1610612745, "Houston Rockets", 3, 5, 56, "Made Shot", "Driving Finger Roll Layup Shot", "2PT Field Goal", "Restricted Area", "Center(C)", "Less Than 8 ft.", 1, -4, 10, 1, 1, "20211211", "MEM", "HOU"], ["Shot Chart Detail", "0022100395", 412, 1628464, "Daniel Theis", 1610612745, "Houston Rockets", 3, 5, 36, "Made Shot", "Turnaround Fadeaway shot", "2PT Field Goal", "In The Paint (Non-RA)", "Center(C)", "Less Than 8 ft.", 6, 51, 46, 1, 1, "20211211", "MEM", "HOU"], ["Shot Chart Detail", "0022100395", 429, 1629717, "Armoni Brooks", 1610612745, "Houston Rockets", 3, 4, 36, "Made Shot", "Pullup Jump shot", "3PT Field Goal", "Above the Break 3", "Right Side Center(RC)", "24+ ft.", 26, 143, 224, 1, 1, "20211211", "MEM", "HOU"], ["Shot Chart Detail", "0022100395", 435, 1630578, "Alperen Sengun", 1610612745, "Houston Rockets", 3, 3, 59, "Made Shot", "Driving Layup Shot", "2PT Field Goal", "Restricted Area", "Center(C)", "Less Than 8 ft.", 1, 6, 14, 1, 1, "20211211", "MEM", "HOU"], ["Shot Chart Detail", "0022100395", 439, 1630231, "Kenyon Martin Jr.", 1610612745, "Houston Rockets", 3, 3, 22, "Made Shot", "Driving Layup Shot", "2PT Field Goal", "In The Paint (Non-RA)", "Center(C)", "Less Than 8 ft.", 5, 7, 55, 1, 1, "20211211", "MEM", "HOU"], ["Shot Chart Detail", "0022100395", 465, 1630231, "Kenyon Martin Jr.", 1610612745, "Houston Rockets", 3, 2, 22, "Made Shot", "Jump Shot", "3PT Field Goal", "Above the Break 3", "Right Side Center(RC)", "24+ ft.", 25, 103, 231, 1, 1, "20211211", "MEM", "HOU"], ["Shot Chart Detail", "0022100395", 469, 1630256, "Jae'Sean Tate", 1610612745, "Houston Rockets", 3, 1, 47, "Missed Shot", "Jump Shot", "3PT Field Goal", "Above the Break 3", "Center(C)", "24+ ft.", 24, -59, 241, 1, 0, "20211211", "MEM", "HOU"], ["Shot Chart Detail", "0022100395", 471, 1630528, "Josh Christopher", 1610612745, "Houston Rockets", 3, 1, 41, "Missed Shot", "Jump Shot", "3PT Field Goal", "Right Corner 3", "Right Side(R)", "24+ ft.", 24, 229, 79, 1, 0, "20211211", "MEM", "HOU"], ["Shot Chart Detail", "0022100395", 484, 1630231, "Kenyon Martin Jr.", 1610612745, "Houston Rockets", 3, 0, 35, "Missed Shot", "Driving Floating Jump Shot", "2PT Field Goal", "In The Paint (Non-RA)", "Center(C)", "Less Than 8 ft.", 6, -1, 63, 1, 0, "20211211", "MEM", "HOU"], ["Shot Chart Detail", "0022100395", 487, 1629717, "Armoni Brooks", 1610612745, "Houston Rockets", 3, 0, 0, "Missed Shot", "Driving Floating Jump Shot", "2PT Field Goal", "Mid-Range", "Right Side(R)", "8-16 ft.", 14, 91, 119, 1, 0, "20211211", "MEM", "HOU"], ["Shot Chart Detail", "0022100395", 511, 1629717, "Armoni Brooks", 1610612745, "Houston Rockets", 4, 11, 10, "Made Shot", "Jump Shot", "3PT Field Goal", "Above the Break 3", "Center(C)", "24+ ft.", 25, -44, 250, 1, 1, "20211211", "MEM", "HOU"], ["Shot Chart Detail", "0022100395", 526, 1630528, "Josh Christopher", 1610612745, "Houston Rockets", 4, 10, 4, "Made Shot", "Driving Reverse Layup Shot", "2PT Field Goal", "Restricted Area", "Center(C)", "Less Than 8 ft.", 0, -6, 5, 1, 1, "20211211", "MEM", "HOU"], ["Shot Chart Detail", "0022100395", 544, 1630578, "Alperen Sengun", 1610612745, "Houston Rockets", 4, 9, 0, "Made Shot", "Driving Layup Shot", "2PT Field Goal", "Restricted Area", "Center(C)", "Less Than 8 ft.", 0, -9, 1, 1, 1, "20211211", "MEM", "HOU"], ["Shot Chart Detail", "0022100395", 550, 1626174, "Christian Wood", 1610612745, "Houston Rockets", 4, 8, 28, "Made Shot", "Layup Shot", "2PT Field Goal", "Restricted Area", "Center(C)", "Less Than 8 ft.", 1, 13, 10, 1, 1, "20211211", "MEM", "HOU"], ["Shot Chart Detail", "0022100395", 565, 1629717, "Armoni Brooks", 1610612745, "Houston Rockets", 4, 7, 21, "Missed Shot", "Pullup Jump shot", "3PT Field Goal", "Above the Break 3", "Left Side Center(LC)", "24+ ft.", 24, -167, 178, 1, 0, "20211211", "MEM", "HOU"], ["Shot Chart Detail", "0022100395", 567, 1630578, "Alperen Sengun", 1610612745, "Houston Rockets", 4, 7, 17, "Made Shot", "Putback Layup Shot", "2PT Field Goal", "Restricted Area", "Center(C)", "Less Than 8 ft.", 1, -18, 3, 1, 1, "20211211", "MEM", "HOU"], ["Shot Chart Detail", "0022100395", 586, 1629726, "Garrison Mathews", 1610612745, "Houston Rockets", 4, 6, 14, "Missed Shot", "Pullup Jump shot", "3PT Field Goal", "Right Corner 3", "Right Side(R)", "24+ ft.", 22, 228, 16, 1, 0, "20211211", "MEM", "HOU"], ["Shot Chart Detail", "0022100395", 588, 1630528, "Josh Christopher", 1610612745, "Houston Rockets", 4, 6, 10, "Made Shot", "Tip Dunk Shot", "2PT Field Goal", "Restricted Area", "Center(C)", "Less Than 8 ft.", 0, 0, 0, 1, 1, "20211211", "MEM", "HOU"], ["Shot Chart Detail", "0022100395", 594, 1630578, "Alperen Sengun", 1610612745, "Houston Rockets", 4, 5, 25, "Made Shot", "Cutting Finger Roll Layup Shot", "2PT Field Goal", "Restricted Area", "Center(C)", "Less Than 8 ft.", 1, 5, 11, 1, 1, "20211211", "MEM", "HOU"], ["Shot Chart Detail", "0022100395", 598, 1626174, "Christian Wood", 1610612745, "Houston Rockets", 4, 4, 58, "Made Shot", "Driving Floating Bank Jump Shot", "2PT Field Goal", "In The Paint (Non-RA)", "Center(C)", "Less Than 8 ft.", 5, -48, 21, 1, 1, "20211211", "MEM", "HOU"], ["Shot Chart Detail", "0022100395", 605, 1629717, "Armoni Brooks", 1610612745, "Houston Rockets", 4, 4, 25, "Missed Shot", "Step Back Jump shot", "3PT Field Goal", "Above the Break 3", "Center(C)", "24+ ft.", 24, 4, 248, 1, 0, "20211211", "MEM", "HOU"], ["Shot Chart Detail", "0022100395", 633, 1626174, "Christian Wood", 1610612745, "Houston Rockets", 4, 3, 19, "Missed Shot", "Driving Floating Jump Shot", "2PT Field Goal", "In The Paint (Non-RA)", "Center(C)", "8-16 ft.", 12, 50, 113, 1, 0, "20211211", "MEM", "HOU"], ["Shot Chart Detail", "0022100395", 635, 1630256, "Jae'Sean Tate", 1610612745, "Houston Rockets", 4, 3, 14, "Made Shot", "Putback Layup Shot", "2PT Field Goal", "Restricted Area", "Center(C)", "Less Than 8 ft.", 0, -7, -4, 1, 1, "20211211", "MEM", "HOU"], ["Shot Chart Detail", "0022100395", 648, 1629726, "Garrison Mathews", 1610612745, "Houston Rockets", 4, 1, 56, "Made Shot", "Jump Bank Shot", "3PT Field Goal", "Above the Break 3", "Right Side Center(RC)", "24+ ft.", 24, 209, 135, 1, 1, "20211211", "MEM", "HOU"], ["Shot Chart Detail", "0022100395", 664, 1626174, "Christian Wood", 1610612745, "Houston Rockets", 4, 1, 2, "Missed Shot", "Jump Shot", "3PT Field Goal", "Above the Break 3", "Left Side Center(LC)", "24+ ft.", 24, -89, 231, 1, 0, "20211211", "MEM", "HOU"], ["Shot Chart Detail", "0022100395", 672, 1629726, "Garrison Mathews", 1610612745, "Houston Rockets", 4, 0, 40, "Missed Shot", "Driving Floating Bank Jump Shot", "2PT Field Goal", "In The Paint (Non-RA)", "Center(C)", "Less Than 8 ft.", 5, -28, 48, 1, 0, "20211211", "MEM", "HOU"], ["Shot Chart Detail", "0022100395", 674, 1626174, "Christian Wood", 1610612745, "Houston Rockets", 4, 0, 38, "Made Shot", "Putback Layup Shot", "2PT Field Goal", "Restricted Area", "Center(C)", "Less Than 8 ft.", 0, 0, 0, 1, 1, "20211211", "MEM", "HOU"], ["Shot Chart Detail", "0022100395", 685, 1629717, "Armoni Brooks", 1610612745, "Houston Rockets", 4, 0, 9, "Made Shot", "Driving Finger Roll Layup Shot", "2PT Field Goal", "Restricted Area", "Center(C)", "Less Than 8 ft.", 1, 16, 3, 1, 1, "20211211", "MEM", "HOU"]]}, {"name": "LeagueAverages", "headers": ["GRID_TYPE", "SHOT_ZONE_BASIC", "SHOT_ZONE_AREA", "SHOT_ZONE_RANGE", "FGA", "FGM", "FG_PCT"], "rowSet": [["League Averages", "Above the Break 3", "Back Court(BC)", "Back Court Shot", 35, 4, 0.114], ["League Averages", "Above the Break 3", "Center(C)", "24+ ft.", 16368, 5613, 0.343], ["League Averages", "Above the Break 3", "Left Side Center(LC)", "24+ ft.", 24924, 8511, 0.341], ["League Averages", "Above the Break 3", "Right Side Center(RC)", "24+ ft.", 23120, 8171, 0.353], ["League Averages", "Backcourt", "Back Court(BC)", "Back Court Shot", 440, 11, 0.025], ["League Averages", "In The Paint (Non-RA)", "Center(C)", "8-16 ft.", 11777, 5228, 0.444], ["League Averages", "In The Paint (Non-RA)", "Center(C)", "Less Than 8 ft.", 23351, 9813, 0.42], ["League Averages", "In The Paint (Non-RA)", "Left Side(L)", "8-16 ft.", 2197, 949, 0.432], ["League Averages", "In The Paint (Non-RA)", "Right Side(R)", "8-16 ft.", 2343, 1000, 0.427], ["League Averages", "Left Corner 3", "Left Side(L)", "24+ ft.", 11377, 4371, 0.384], ["League Averages", "Mid-Range", "Center(C)", "8-16 ft.", 2088, 921, 0.441], ["League Averages", "Mid-Range", "Center(C)", "16-24 ft.", 4165, 1743, 0.418], ["League Averages", "Mid-Range", "Left Side Center(LC)", "16-24 ft.", 3972, 1632, 0.411], ["League Averages", "Mid-Range", "Left Side(L)", "8-16 ft.", 5014, 2023, 0.403], ["League Averages", "Mid-Range", "Left Side(L)", "16-24 ft.", 1680, 613, 0.365], ["League Averages", "Mid-Range", "Right Side Center(RC)", "16-24 ft.", 4043, 1575, 0.39], ["League Averages", "Mid-Range", "Right Side(R)", "16-24 ft.", 1609, 614, 0.382], ["League Averages", "Mid-Range", "Right Side(R)", "8-16 ft.", 5141, 2143, 0.417], ["League Averages", "Restricted Area", "Center(C)", "Less Than 8 ft.", 62987, 41140, 0.653], ["League Averages", "Right Corner 3", "Right Side(R)", "24+ ft.", 10091, 3855, 0.382]]}]}